df_loader/__init__.py
df_loader/read_sql.py
df_loader/pandas_sql_loader/__init__.py
df_loader/pandas_sql_loader/downcast.py
df_loader/pandas_wrapper/__init__.py
df_loader/pandas_wrapper/from_records.py
df_loader/pandas_wrapper/read_db.py
df_loader/pandas_wrapper/read_sql.py
df_loader/pandas_wrapper/read_sqlite.py
df_loader/pandas_wrapper/read_table.py
df_loader/pandas_wrapper/to_arrays.py
df_loader/pandas_wrapper/wrap_result.py
df_loader-1.0.4.dist-info/METADATA
df_loader-1.0.4.dist-info/WHEEL
df_loader-1.0.4.dist-info/top_level.txt
df_loader-1.0.4.dist-info/RECORD
