Metadata-Version: 2.1
Name: df-loader
Version: 1.0.4
Summary: To optimization load DataFrame from databases
Home-page: UNKNOWN
Author: Karev Vitaliy
Author-email: Vitaliy.Karev@mvideo.ru
License: MIT
Platform: UNKNOWN
Requires-Dist: certifi (==2019.9.11)
Requires-Dist: memory-profiler (==0.55.0)
Requires-Dist: numpy (==1.17.4)
Requires-Dist: pandas (==0.25.3)
Requires-Dist: psutil (==5.6.5)
Requires-Dist: python-dateutil (==2.8.1)
Requires-Dist: pytz (==2019.3)
Requires-Dist: six (==1.13.0)
Requires-Dist: SQLAlchemy (==1.3.11)
